mdtk/__init__.py
mdtk/_version.py
mdtk/bookmarks.py
mdtk-0.1.0.dist-info/METADATA
mdtk-0.1.0.dist-info/WHEEL
mdtk-0.1.0.dist-info/entry_points.txt
mdtk-0.1.0.dist-info/top_level.txt
mdtk-0.1.0.dist-info/RECORD
